pyndoc/__init__.py
pyndoc/__main__.py
pyndoc/_latex.py
pyndoc/filter.py
pyndoc/formats.py
pyndoc/latex.py
pyndoc/markdown.py
pyndoc/preprocess.py
pyndoc/server.py
pyndoc/server_utils.py
pyndoc-0.1.6.dist-info/LICENSE
pyndoc-0.1.6.dist-info/METADATA
pyndoc-0.1.6.dist-info/WHEEL
pyndoc-0.1.6.dist-info/entry_points.txt
pyndoc-0.1.6.dist-info/top_level.txt
pyndoc-0.1.6.dist-info/RECORD
