Metadata-Version: 2.2
Name: pyndoc
Version: 0.1.6
Summary: A standalone Pandoc filter and optional preprocessor to include arbitrary Python code in Markdown documents, ran at build time.
Author: Peter Brookes Chambers
Project-URL: Homepage, https://github.com/ech0-chambers/pyndoc
Classifier: Programming Language :: Python :: 3
Classifier: License :: OSI Approved :: GNU Affero General Public License v3
Classifier: Operating System :: OS Independent
Requires-Python: >=3.8
License-File: LICENSE
Requires-Dist: panflute
Requires-Dist: pyyaml
Requires-Dist: pint
